{
  "/_app": "pages/_app.js",
  "/_error": "pages/_error.js",
  "/404": "pages/404.html",
  "/_document": "pages/_document.js",
  "/about": "pages/about.html",
  "/disclaimer": "pages/disclaimer.html",
  "/contact": "pages/contact.html",
  "/api/compound": "pages/api/compound.js",
  "/en": "pages/en.html",
  "/en/tools/calculator": "pages/en/tools/calculator.html",
  "/ko/tools/calculator": "pages/ko/tools/calculator.html",
  "/ko": "pages/ko.html",
  "/privacy": "pages/privacy.html",
  "/tools/compound-interest": "pages/tools/compound-interest.html",
  "/tools": "pages/tools.html",
  "/tools/goal-simulator": "pages/tools/goal-simulator.html",
  "/terms": "pages/terms.html",
  "/category/[slug]": "pages/category/[slug].js",
  "/en/blog": "pages/en/blog.js",
  "/": "pages/index.js",
  "/ko/blog/[slug]": "pages/ko/blog/[slug].js",
  "/ko/blog": "pages/ko/blog.js",
  "/en/blog/[slug]": "pages/en/blog/[slug].js",
  "/posts/[slug]": "pages/posts/[slug].js"
}